Workbook

Sheet 订单明细
A1: 2026年10月销售订单明细（自动生成）
A2: 统计期间 | B2: 2026-10
A3: 订单编号 | B3: 订单日期 | C3: 客户编号 | D3: 客户名称 | E3: 城市 | F3: 商品编号 | G3: 商品名称 | H3: 分类 | I3: 数量 | J3: 单价 | K3: 原价金额 | L3: 折扣率 | M3: 优惠金额 | N3: 运费 | O3: 应付金额 | P3: 币种 | Q3: 已付款 | R3: 订单状态 | S3: 销售员 | T3: 渠道 | U3: 省份 | V3: 收件人 | W3: 电话 | X3: 备注 | Y3: 外部流水号 | Z3: 退货数量 | AA3: 发票抬头 | AB3: 发票已开 | AC3: 预留空列 | AD3: 税率 | AE3: 预计发货日期 | AF3: 校验备注
A4: ORD-202610-100001 | B4: 45900.5 | C4: C001 | D4: ='客户档案'!B3 -> 张三 | E4: 上海 | F4: P001 | G4: ='商品目录'!B3 -> 机械键盘 | H4: 外设 | I4: 2 | J4: 99 | K4: =I4*J4 -> 198 | L4: 0 | M4: =K4*L4 -> 0 | N4: 0 | O4: =K4-M4+N4 -> 198 | P4: CNY | Q4: FALSE | R4: 待付款 | S4: 李四 | T4: 网页 | U4: 上海 | V4: 张三 | W4: 0138000100001 | Y4: 9.0071993e+15 | Z4: 2 | AA4: 张三 | AB4: FALSE | AD4: 0.125 | AE4: 45902.5 | AF4: #N/A
A5: ORD-202610-100002 | B5: 45901.5 | C5: C002 | D5: ='客户档案'!B4 -> Acme, Inc. | E5: 北京 | F5: P002 | G5: ='商品目录'!B4 -> 显示器 | H5: 显示设备 | I5: 4 | J5: 129 | K5: =I5*J5 -> 516 | L5: 0.5 | M5: =K5*L5 -> 258 | N5: 10 | O5: =K5-M5+N5 -> 268 | P5: CNY | Q5: TRUE | R5: 已完成 | S5: 王五 | T5: 门店 | U5: 北京 | V5: Acme, Inc. | W5: 0138000100002 | X5: 加急,周五前送达 | Y5: 9.0071993e+15 | Z5: 0 | AA5: Acme, Inc. | AB5: TRUE | AD5: 0.125 | AE5: 45903.5 | AF5: 正常
A6: ORD-202610-100003 | B6: 45902.5 | C6: C003 | D6: ='客户档案'!B5 -> 研发"中心" | E6: 深圳 | F6: P003 | G6: ='商品目录'!B5 -> 办公椅 | H6: 家具 | I6: 6 | J6: 45 | K6: =I6*J6 -> 270 | L6: 0 | M6: =K6*L6 -> 0 | N6: 20 | O6: =K6-M6+N6 -> 290 | P6: CNY | Q6: TRUE | R6: 已完成 | S6: 赵六 | T6: API | U6: 广东 | V6: 研发"中心" | W6: 0138000100003 | X6: 收货前联系"前台" | Y6: 9.0071993e+15 | Z6: 0 | AA6: 研发"中心" | AB6: FALSE | AD6: 0.125 | AE6: 45904.5 | AF6: 正常
A7: ORD-202610-100004 | B7: 45903.5 | C7: C001 | D7: ='客户档案'!B3 -> 张三 | E7: 杭州 | F7: P004 | G7: ='商品目录'!B6 -> 多功能"支架" | H7: 配件 | I7: 8 | J7: 8 | K7: =I7*J7 -> 64 | L7: 0.5 | M7: =K7*L7 -> 32 | N7: 0 | O7: =K7-M7+N7 -> 32 | P7: CNY | Q7: TRUE | R7: 已完成 | S7: 李四 | T7: 网页 | U7: 浙江 | V7: 张三 | W7: 0138000100004 | X7: 第一行 第二行 | Y7: 9.0071993e+15 | Z7: 0 | AA7: 张三 | AB7: TRUE | AD7: 0.125 | AE7: 45905.5 | AF7: 正常
A8: ORD-202610-100005 | B8: 45904.5 | C8: C002 | D8: ='客户档案'!B4 -> Acme, Inc. | E8: 上海 | F8: P001 | G8: ='商品目录'!B3 -> 机械键盘 | H8: 外设 | I8: 10 | J8: 99 | K8: =I8*J8 -> 990 | L8: 0 | M8: =K8*L8 -> 0 | N8: 10 | O8: =K8-M8+N8 -> 1000 | P8: CNY | Q8: FALSE | R8: 待付款 | S8: 王五 | T8: 门店 | U8: 上海 | V8: Acme, Inc. | W8: 0138000100005 | Y8: 9.0071993e+15 | Z8: 0 | AA8: Acme, Inc. | AB8: FALSE | AD8: 0.125 | AE8: 45906.5 | AF8: 正常
A9: ORD-202610-100006 | B9: 45905.5 | C9: C003 | D9: ='客户档案'!B5 -> 研发"中心" | E9: 北京 | F9: P002 | G9: ='商品目录'!B4 -> 显示器 | H9: 显示设备 | I9: 2 | J9: 129 | K9: =I9*J9 -> 258 | L9: 0.5 | M9: =K9*L9 -> 129 | N9: 20 | O9: =K9-M9+N9 -> 149 | P9: CNY | Q9: TRUE | R9: 已完成 | S9: 赵六 | T9: API | U9: 北京 | V9: 研发"中心" | W9: 0138000100006 | X9: 加急,周五前送达 | Y9: 9.0071993e+15 | Z9: 0 | AA9: 研发"中心" | AB9: TRUE | AD9: 0.125 | AE9: 45907.5 | AF9: 正常
A10: ORD-202610-100007 | B10: 45906.5 | C10: C001 | D10: ='客户档案'!B3 -> 张三 | E10: 深圳 | F10: P003 | G10: ='商品目录'!B5 -> 办公椅 | H10: 家具 | I10: 4 | J10: 45 | K10: =I10*J10 -> 180 | L10: 0 | M10: =K10*L10 -> 0 | N10: 0 | O10: =K10-M10+N10 -> 180 | P10: CNY | Q10: TRUE | R10: 已完成 | S10: 李四 | T10: 网页 | U10: 广东 | V10: 张三 | W10: 0138000100007 | X10: 收货前联系"前台" | Y10: 9.0071993e+15 | Z10: 0 | AA10: 张三 | AB10: FALSE | AD10: 0.125 | AE10: 45908.5 | AF10: 正常
A11: ORD-202610-100008 | B11: 45907.5 | C11: C002 | D11: ='客户档案'!B4 -> Acme, Inc. | E11: 杭州 | F11: P004 | G11: ='商品目录'!B6 -> 多功能"支架" | H11: 配件 | I11: 6 | J11: 8 | K11: =I11*J11 -> 48 | L11: 0.5 | M11: =K11*L11 -> 24 | N11: 10 | O11: =K11-M11+N11 -> 34 | P11: CNY | Q11: TRUE | R11: 已完成 | S11: 王五 | T11: 门店 | U11: 浙江 | V11: Acme, Inc. | W11: 0138000100008 | X11: 第一行 第二行 | Y11: 9.0071993e+15 | Z11: 0 | AA11: Acme, Inc. | AB11: TRUE | AD11: 0.125 | AE11: 45909.5 | AF11: 正常
A12: ORD-202610-100009 | B12: 45908.5 | C12: C003 | D12: ='客户档案'!B5 -> 研发"中心" | E12: 上海 | F12: P001 | G12: ='商品目录'!B3 -> 机械键盘 | H12: 外设 | I12: 8 | J12: 99 | K12: =I12*J12 -> 792 | L12: 0 | M12: =K12*L12 -> 0 | N12: 20 | O12: =K12-M12+N12 -> 812 | P12: CNY | Q12: FALSE | R12: 待付款 | S12: 赵六 | T12: API | U12: 上海 | V12: 研发"中心" | W12: 0138000100009 | Y12: 9.0071993e+15 | Z12: 0 | AA12: 研发"中心" | AB12: FALSE | AD12: 0.125 | AE12: 45910.5 | AF12: 正常
A13: ORD-202610-100010 | B13: 45909.5 | C13: C001 | D13: ='客户档案'!B3 -> 张三 | E13: 北京 | F13: P002 | G13: ='商品目录'!B4 -> 显示器 | H13: 显示设备 | I13: 10 | J13: 129 | K13: =I13*J13 -> 1290 | L13: 0.5 | M13: =K13*L13 -> 645 | N13: 0 | O13: =K13-M13+N13 -> 645 | P13: CNY | Q13: TRUE | R13: 已完成 | S13: 李四 | T13: 网页 | U13: 北京 | V13: 张三 | W13: 0138000100010 | X13: 加急,周五前送达 | Y13: 9.0071993e+15 | Z13: 0 | AA13: 张三 | AB13: TRUE | AD13: 0.125 | AE13: 45911.5 | AF13: 正常
A14: ORD-202610-100011 | B14: 45910.5 | C14: C002 | D14: ='客户档案'!B4 -> Acme, Inc. | E14: 深圳 | F14: P003 | G14: ='商品目录'!B5 -> 办公椅 | H14: 家具 | I14: 2 | J14: 45 | K14: =I14*J14 -> 90 | L14: 0 | M14: =K14*L14 -> 0 | N14: 10 | O14: =K14-M14+N14 -> 100 | P14: CNY | Q14: TRUE | R14: 已完成 | S14: 王五 | T14: 门店 | U14: 广东 | V14: Acme, Inc. | W14: 0138000100011 | X14: 收货前联系"前台" | Y14: 9.0071993e+15 | Z14: 0 | AA14: Acme, Inc. | AB14: FALSE | AD14: 0.125 | AE14: 45912.5 | AF14: 正常
A15: ORD-202610-100012 | B15: 45911.5 | C15: C003 | D15: ='客户档案'!B5 -> 研发"中心" | E15: 杭州 | F15: P004 | G15: ='商品目录'!B6 -> 多功能"支架" | H15: 配件 | I15: 4 | J15: 8 | K15: =I15*J15 -> 32 | L15: 0.5 | M15: =K15*L15 -> 16 | N15: 20 | O15: =K15-M15+N15 -> 36 | P15: CNY | Q15: TRUE | R15: 已完成 | S15: 赵六 | T15: API | U15: 浙江 | V15: 研发"中心" | W15: 0138000100012 | X15: 第一行 第二行 | Y15: 9.0071993e+15 | Z15: 0 | AA15: 研发"中心" | AB15: TRUE | AD15: 0.125 | AE15: 45913.5 | AF15: 正常
A16: ORD-202610-100013 | B16: 45912.5 | C16: C001 | D16: ='客户档案'!B3 -> 张三 | E16: 上海 | F16: P001 | G16: ='商品目录'!B3 -> 机械键盘 | H16: 外设 | I16: 6 | J16: 99 | K16: =I16*J16 -> 594 | L16: 0 | M16: =K16*L16 -> 0 | N16: 0 | O16: =K16-M16+N16 -> 594 | P16: CNY | Q16: FALSE | R16: 待付款 | S16: 李四 | T16: 网页 | U16: 上海 | V16: 张三 | W16: 0138000100013 | Y16: 9.0071993e+15 | Z16: 0 | AA16: 张三 | AB16: FALSE | AD16: 0.125 | AE16: 45914.5 | AF16: 正常
A17: ORD-202610-100014 | B17: 45913.5 | C17: C002 | D17: ='客户档案'!B4 -> Acme, Inc. | E17: 北京 | F17: P002 | G17: ='商品目录'!B4 -> 显示器 | H17: 显示设备 | I17: 8 | J17: 129 | K17: =I17*J17 -> 1032 | L17: 0.5 | M17: =K17*L17 -> 516 | N17: 10 | O17: =K17-M17+N17 -> 526 | P17: CNY | Q17: TRUE | R17: 已完成 | S17: 王五 | T17: 门店 | U17: 北京 | V17: Acme, Inc. | W17: 0138000100014 | X17: 加急,周五前送达 | Y17: 9.0071993e+15 | Z17: 0 | AA17: Acme, Inc. | AB17: TRUE | AD17: 0.125 | AE17: 45915.5 | AF17: 正常
A18: ORD-202610-100015 | B18: 45914.5 | C18: C003 | D18: ='客户档案'!B5 -> 研发"中心" | E18: 深圳 | F18: P003 | G18: ='商品目录'!B5 -> 办公椅 | H18: 家具 | I18: 10 | J18: 45 | K18: =I18*J18 -> 450 | L18: 0 | M18: =K18*L18 -> 0 | N18: 20 | O18: =K18-M18+N18 -> 470 | P18: CNY | Q18: TRUE | R18: 已完成 | S18: 赵六 | T18: API | U18: 广东 | V18: 研发"中心" | W18: 0138000100015 | X18: 收货前联系"前台" | Y18: 9.0071993e+15 | Z18: 0 | AA18: 研发"中心" | AB18: FALSE | AD18: 0.125 | AE18: 45916.5 | AF18: 正常
A19: ORD-202610-100016 | B19: 45915.5 | C19: C001 | D19: ='客户档案'!B3 -> 张三 | E19: 杭州 | F19: P004 | G19: ='商品目录'!B6 -> 多功能"支架" | H19: 配件 | I19: 2 | J19: 8 | K19: =I19*J19 -> 16 | L19: 0.5 | M19: =K19*L19 -> 8 | N19: 0 | O19: =K19-M19+N19 -> 8 | P19: CNY | Q19: TRUE | R19: 已完成 | S19: 李四 | T19: 网页 | U19: 浙江 | V19: 张三 | W19: 0138000100016 | X19: 第一行 第二行 | Y19: 9.0071993e+15 | Z19: 0 | AA19: 张三 | AB19: TRUE | AD19: 0.125 | AE19: 45917.5 | AF19: 正常
A20: ORD-202610-100017 | B20: 45916.5 | C20: C002 | D20: ='客户档案'!B4 -> Acme, Inc. | E20: 上海 | F20: P001 | G20: ='商品目录'!B3 -> 机械键盘 | H20: 外设 | I20: 4 | J20: 99 | K20: =I20*J20 -> 396 | L20: 0 | M20: =K20*L20 -> 0 | N20: 10 | O20: =K20-M20+N20 -> 406 | P20: CNY | Q20: FALSE | R20: 待付款 | S20: 王五 | T20: 门店 | U20: 上海 | V20: Acme, Inc. | W20: 0138000100017 | Y20: 9.0071993e+15 | Z20: 0 | AA20: Acme, Inc. | AB20: FALSE | AD20: 0.125 | AE20: 45918.5 | AF20: 正常
A21: ORD-202610-100018 | B21: 45917.5 | C21: C003 | D21: ='客户档案'!B5 -> 研发"中心" | E21: 北京 | F21: P002 | G21: ='商品目录'!B4 -> 显示器 | H21: 显示设备 | I21: 6 | J21: 129 | K21: =I21*J21 -> 774 | L21: 0.5 | M21: =K21*L21 -> 387 | N21: 20 | O21: =K21-M21+N21 -> 407 | P21: CNY | Q21: TRUE | R21: 已完成 | S21: 赵六 | T21: API | U21: 北京 | V21: 研发"中心" | W21: 0138000100018 | X21: 加急,周五前送达 | Y21: 9.0071993e+15 | Z21: 2 | AA21: 研发"中心" | AB21: TRUE | AD21: 0.125 | AE21: 45919.5 | AF21: 正常
A22: ORD-202610-100019 | B22: 45918.5 | C22: C001 | D22: ='客户档案'!B3 -> 张三 | E22: 深圳 | F22: P003 | G22: ='商品目录'!B5 -> 办公椅 | H22: 家具 | I22: 8 | J22: 45 | K22: =I22*J22 -> 360 | L22: 0 | M22: =K22*L22 -> 0 | N22: 0 | O22: =K22-M22+N22 -> 360 | P22: CNY | Q22: TRUE | R22: 已完成 | S22: 李四 | T22: 网页 | U22: 广东 | V22: 张三 | W22: 0138000100019 | X22: 收货前联系"前台" | Y22: 9.0071993e+15 | Z22: 0 | AA22: 张三 | AB22: FALSE | AD22: 0.125 | AE22: 45920.5 | AF22: 正常
A23: ORD-202610-100020 | B23: 45919.5 | C23: C002 | D23: ='客户档案'!B4 -> Acme, Inc. | E23: 杭州 | F23: P004 | G23: ='商品目录'!B6 -> 多功能"支架" | H23: 配件 | I23: 10 | J23: 8 | K23: =I23*J23 -> 80 | L23: 0.5 | M23: =K23*L23 -> 40 | N23: 10 | O23: =K23-M23+N23 -> 50 | P23: CNY | Q23: TRUE | R23: 已完成 | S23: 王五 | T23: 门店 | U23: 浙江 | V23: Acme, Inc. | W23: 0138000100020 | X23: 第一行 第二行 | Y23: 9.0071993e+15 | Z23: 0 | AA23: Acme, Inc. | AB23: TRUE | AD23: 0.125 | AE23: 45921.5 | AF23: 正常
A24: ORD-202610-100021 | B24: 45920.5 | C24: C003 | D24: ='客户档案'!B5 -> 研发"中心" | E24: 上海 | F24: P001 | G24: ='商品目录'!B3 -> 机械键盘 | H24: 外设 | I24: 2 | J24: 99 | K24: =I24*J24 -> 198 | L24: 0 | M24: =K24*L24 -> 0 | N24: 20 | O24: =K24-M24+N24 -> 218 | P24: CNY | Q24: FALSE | R24: 待付款 | S24: 赵六 | T24: API | U24: 上海 | V24: 研发"中心" | W24: 0138000100021 | Y24: 9.0071993e+15 | Z24: 0 | AA24: 研发"中心" | AB24: FALSE | AD24: 0.125 | AE24: 45922.5 | AF24: 正常
A25: ORD-202610-100022 | B25: 45921.5 | C25: C001 | D25: ='客户档案'!B3 -> 张三 | E25: 北京 | F25: P002 | G25: ='商品目录'!B4 -> 显示器 | H25: 显示设备 | I25: 4 | J25: 129 | K25: =I25*J25 -> 516 | L25: 0.5 | M25: =K25*L25 -> 258 | N25: 0 | O25: =K25-M25+N25 -> 258 | P25: CNY | Q25: TRUE | R25: 已完成 | S25: 李四 | T25: 网页 | U25: 北京 | V25: 张三 | W25: 0138000100022 | X25: 加急,周五前送达 | Y25: 9.0071993e+15 | Z25: 0 | AA25: 张三 | AB25: TRUE | AD25: 0.125 | AE25: 45923.5 | AF25: 正常
A26: ORD-202610-100023 | B26: 45922.5 | C26: C002 | D26: ='客户档案'!B4 -> Acme, Inc. | E26: 深圳 | F26: P003 | G26: ='商品目录'!B5 -> 办公椅 | H26: 家具 | I26: 6 | J26: 45 | K26: =I26*J26 -> 270 | L26: 0 | M26: =K26*L26 -> 0 | N26: 10 | O26: =K26-M26+N26 -> 280 | P26: CNY | Q26: TRUE | R26: 已完成 | S26: 王五 | T26: 门店 | U26: 广东 | V26: Acme, Inc. | W26: 0138000100023 | X26: 收货前联系"前台" | Y26: 9.0071993e+15 | Z26: 0 | AA26: Acme, Inc. | AB26: FALSE | AD26: 0.125 | AE26: 45924.5 | AF26: 正常
A27: ORD-202610-100024 | B27: 45923.5 | C27: C003 | D27: ='客户档案'!B5 -> 研发"中心" | E27: 杭州 | F27: P004 | G27: ='商品目录'!B6 -> 多功能"支架" | H27: 配件 | I27: 8 | J27: 8 | K27: =I27*J27 -> 64 | L27: 0.5 | M27: =K27*L27 -> 32 | N27: 20 | O27: =K27-M27+N27 -> 52 | P27: CNY | Q27: TRUE | R27: 已完成 | S27: 赵六 | T27: API | U27: 浙江 | V27: 研发"中心" | W27: 0138000100024 | X27: 第一行 第二行 | Y27: 9.0071993e+15 | Z27: 0 | AA27: 研发"中心" | AB27: TRUE | AD27: 0.125 | AE27: 45925.5 | AF27: 正常
A28: ORD-202610-100025 | B28: 45924.5 | C28: C001 | D28: ='客户档案'!B3 -> 张三 | E28: 上海 | F28: P001 | G28: ='商品目录'!B3 -> 机械键盘 | H28: 外设 | I28: 10 | J28: 99 | K28: =I28*J28 -> 990 | L28: 0 | M28: =K28*L28 -> 0 | N28: 0 | O28: =K28-M28+N28 -> 990 | P28: CNY | Q28: FALSE | R28: 待付款 | S28: 李四 | T28: 网页 | U28: 上海 | V28: 张三 | W28: 0138000100025 | Y28: 9.0071993e+15 | Z28: 0 | AA28: 张三 | AB28: FALSE | AD28: 0.125 | AE28: 45926.5 | AF28: 正常
A29: ORD-202610-100026 | B29: 45925.5 | C29: C002 | D29: ='客户档案'!B4 -> Acme, Inc. | E29: 北京 | F29: P002 | G29: ='商品目录'!B4 -> 显示器 | H29: 显示设备 | I29: 2 | J29: 129 | K29: =I29*J29 -> 258 | L29: 0.5 | M29: =K29*L29 -> 129 | N29: 10 | O29: =K29-M29+N29 -> 139 | P29: CNY | Q29: TRUE | R29: 已完成 | S29: 王五 | T29: 门店 | U29: 北京 | V29: Acme, Inc. | W29: 0138000100026 | X29: 加急,周五前送达 | Y29: 9.0071993e+15 | Z29: 0 | AA29: Acme, Inc. | AB29: TRUE | AD29: 0.125 | AE29: 45927.5 | AF29: 正常
A30: ORD-202610-100027 | B30: 45926.5 | C30: C003 | D30: ='客户档案'!B5 -> 研发"中心" | E30: 深圳 | F30: P003 | G30: ='商品目录'!B5 -> 办公椅 | H30: 家具 | I30: 4 | J30: 45 | K30: =I30*J30 -> 180 | L30: 0 | M30: =K30*L30 -> 0 | N30: 20 | O30: =K30-M30+N30 -> 200 | P30: CNY | Q30: TRUE | R30: 已完成 | S30: 赵六 | T30: API | U30: 广东 | V30: 研发"中心" | W30: 0138000100027 | X30: 收货前联系"前台" | Y30: 9.0071993e+15 | Z30: 0 | AA30: 研发"中心" | AB30: FALSE | AD30: 0.125 | AE30: 45928.5 | AF30: 正常
A31: ORD-202610-100028 | B31: 45927.5 | C31: C001 | D31: ='客户档案'!B3 -> 张三 | E31: 杭州 | F31: P004 | G31: ='商品目录'!B6 -> 多功能"支架" | H31: 配件 | I31: 6 | J31: 8 | K31: =I31*J31 -> 48 | L31: 0.5 | M31: =K31*L31 -> 24 | N31: 0 | O31: =K31-M31+N31 -> 24 | P31: CNY | Q31: TRUE | R31: 已完成 | S31: 李四 | T31: 网页 | U31: 浙江 | V31: 张三 | W31: 0138000100028 | X31: 第一行 第二行 | Y31: 9.0071993e+15 | Z31: 0 | AA31: 张三 | AB31: TRUE | AD31: 0.125 | AE31: 45929.5 | AF31: 正常
A32: ORD-202610-100029 | B32: 45900.5 | C32: C002 | D32: ='客户档案'!B4 -> Acme, Inc. | E32: 上海 | F32: P001 | G32: ='商品目录'!B3 -> 机械键盘 | H32: 外设 | I32: 8 | J32: 99 | K32: =I32*J32 -> 792 | L32: 0 | M32: =K32*L32 -> 0 | N32: 10 | O32: =K32-M32+N32 -> 802 | P32: CNY | Q32: FALSE | R32: 待付款 | S32: 王五 | T32: 门店 | U32: 上海 | V32: Acme, Inc. | W32: 0138000100029 | Y32: 9.0071993e+15 | Z32: 0 | AA32: Acme, Inc. | AB32: FALSE | AD32: 0.125 | AE32: 45902.5 | AF32: 正常
A33: ORD-202610-100030 | B33: 45901.5 | C33: C003 | D33: ='客户档案'!B5 -> 研发"中心" | E33: 北京 | F33: P002 | G33: ='商品目录'!B4 -> 显示器 | H33: 显示设备 | I33: 10 | J33: 129 | K33: =I33*J33 -> 1290 | L33: 0.5 | M33: =K33*L33 -> 645 | N33: 20 | O33: =K33-M33+N33 -> 665 | P33: CNY | Q33: TRUE | R33: 已完成 | S33: 赵六 | T33: API | U33: 北京 | V33: 研发"中心" | W33: 0138000100030 | X33: 加急,周五前送达 | Y33: 9.0071993e+15 | Z33: 0 | AA33: 研发"中心" | AB33: TRUE | AD33: 0.125 | AE33: 45903.5 | AF33: 正常
A34: ORD-202610-100031 | B34: 45902.5 | C34: C001 | D34: ='客户档案'!B3 -> 张三 | E34: 深圳 | F34: P003 | G34: ='商品目录'!B5 -> 办公椅 | H34: 家具 | I34: 2 | J34: 45 | K34: =I34*J34 -> 90 | L34: 0 | M34: =K34*L34 -> 0 | N34: 0 | O34: =K34-M34+N34 -> 90 | P34: CNY | Q34: TRUE | R34: 已完成 | S34: 李四 | T34: 网页 | U34: 广东 | V34: 张三 | W34: 0138000100031 | X34: 收货前联系"前台" | Y34: 9.0071993e+15 | Z34: 0 | AA34: 张三 | AB34: FALSE | AD34: 0.125 | AE34: 45904.5 | AF34: 正常
A35: ORD-202610-100032 | B35: 45903.5 | C35: C002 | D35: ='客户档案'!B4 -> Acme, Inc. | E35: 杭州 | F35: P004 | G35: ='商品目录'!B6 -> 多功能"支架" | H35: 配件 | I35: 4 | J35: 8 | K35: =I35*J35 -> 32 | L35: 0.5 | M35: =K35*L35 -> 16 | N35: 10 | O35: =K35-M35+N35 -> 26 | P35: CNY | Q35: TRUE | R35: 已完成 | S35: 王五 | T35: 门店 | U35: 浙江 | V35: Acme, Inc. | W35: 0138000100032 | X35: 第一行 第二行 | Y35: 9.0071993e+15 | Z35: 0 | AA35: Acme, Inc. | AB35: TRUE | AD35: 0.125 | AE35: 45905.5 | AF35: 正常
A36: ORD-202610-100033 | B36: 45904.5 | C36: C003 | D36: ='客户档案'!B5 -> 研发"中心" | E36: 上海 | F36: P001 | G36: ='商品目录'!B3 -> 机械键盘 | H36: 外设 | I36: 6 | J36: 99 | K36: =I36*J36 -> 594 | L36: 0 | M36: =K36*L36 -> 0 | N36: 20 | O36: =K36-M36+N36 -> 614 | P36: CNY | Q36: FALSE | R36: 待付款 | S36: 赵六 | T36: API | U36: 上海 | V36: 研发"中心" | W36: 0138000100033 | Y36: 9.0071993e+15 | Z36: 0 | AA36: 研发"中心" | AB36: FALSE | AD36: 0.125 | AE36: 45906.5 | AF36: 正常
A37: ORD-202610-100034 | B37: 45905.5 | C37: C001 | D37: ='客户档案'!B3 -> 张三 | E37: 北京 | F37: P002 | G37: ='商品目录'!B4 -> 显示器 | H37: 显示设备 | I37: 8 | J37: 129 | K37: =I37*J37 -> 1032 | L37: 0.5 | M37: =K37*L37 -> 516 | N37: 0 | O37: =K37-M37+N37 -> 516 | P37: CNY | Q37: TRUE | R37: 已完成 | S37: 李四 | T37: 网页 | U37: 北京 | V37: 张三 | W37: 0138000100034 | X37: 加急,周五前送达 | Y37: 9.0071993e+15 | Z37: 0 | AA37: 张三 | AB37: TRUE | AD37: 0.125 | AE37: 45907.5 | AF37: 正常
A38: ORD-202610-100035 | B38: 45906.5 | C38: C002 | D38: ='客户档案'!B4 -> Acme, Inc. | E38: 深圳 | F38: P003 | G38: ='商品目录'!B5 -> 办公椅 | H38: 家具 | I38: 10 | J38: 45 | K38: =I38*J38 -> 450 | L38: 0 | M38: =K38*L38 -> 0 | N38: 10 | O38: =K38-M38+N38 -> 460 | P38: CNY | Q38: TRUE | R38: 已完成 | S38: 王五 | T38: 门店 | U38: 广东 | V38: Acme, Inc. | W38: 0138000100035 | X38: 收货前联系"前台" | Y38: 9.0071993e+15 | Z38: 2 | AA38: Acme, Inc. | AB38: FALSE | AD38: 0.125 | AE38: 45908.5 | AF38: 正常
A39: ORD-202610-100036 | B39: 45907.5 | C39: C003 | D39: ='客户档案'!B5 -> 研发"中心" | E39: 杭州 | F39: P004 | G39: ='商品目录'!B6 -> 多功能"支架" | H39: 配件 | I39: 2 | J39: 8 | K39: =I39*J39 -> 16 | L39: 0.5 | M39: =K39*L39 -> 8 | N39: 20 | O39: =K39-M39+N39 -> 28 | P39: CNY | Q39: TRUE | R39: 已完成 | S39: 赵六 | T39: API | U39: 浙江 | V39: 研发"中心" | W39: 0138000100036 | X39: 第一行 第二行 | Y39: 9.0071993e+15 | Z39: 0 | AA39: 研发"中心" | AB39: TRUE | AD39: 0.125 | AE39: 45909.5 | AF39: 正常
A40: ORD-202610-100037 | B40: 45908.5 | C40: C001 | D40: ='客户档案'!B3 -> 张三 | E40: 上海 | F40: P001 | G40: ='商品目录'!B3 -> 机械键盘 | H40: 外设 | I40: 4 | J40: 99 | K40: =I40*J40 -> 396 | L40: 0 | M40: =K40*L40 -> 0 | N40: 0 | O40: =K40-M40+N40 -> 396 | P40: CNY | Q40: FALSE | R40: 待付款 | S40: 李四 | T40: 网页 | U40: 上海 | V40: 张三 | W40: 0138000100037 | Y40: 9.0071993e+15 | Z40: 0 | AA40: 张三 | AB40: FALSE | AD40: 0.125 | AE40: 45910.5 | AF40: 正常
A41: ORD-202610-100038 | B41: 45909.5 | C41: C002 | D41: ='客户档案'!B4 -> Acme, Inc. | E41: 北京 | F41: P002 | G41: ='商品目录'!B4 -> 显示器 | H41: 显示设备 | I41: 6 | J41: 129 | K41: =I41*J41 -> 774 | L41: 0.5 | M41: =K41*L41 -> 387 | N41: 10 | O41: =K41-M41+N41 -> 397 | P41: CNY | Q41: TRUE | R41: 已完成 | S41: 王五 | T41: 门店 | U41: 北京 | V41: Acme, Inc. | W41: 0138000100038 | X41: 加急,周五前送达 | Y41: 9.0071993e+15 | Z41: 0 | AA41: Acme, Inc. | AB41: TRUE | AD41: 0.125 | AE41: 45911.5 | AF41: 正常
A42: ORD-202610-100039 | B42: 45910.5 | C42: C003 | D42: ='客户档案'!B5 -> 研发"中心" | E42: 深圳 | F42: P003 | G42: ='商品目录'!B5 -> 办公椅 | H42: 家具 | I42: 8 | J42: 45 | K42: =I42*J42 -> 360 | L42: 0 | M42: =K42*L42 -> 0 | N42: 20 | O42: =K42-M42+N42 -> 380 | P42: CNY | Q42: TRUE | R42: 已完成 | S42: 赵六 | T42: API | U42: 广东 | V42: 研发"中心" | W42: 0138000100039 | X42: 收货前联系"前台" | Y42: 9.0071993e+15 | Z42: 0 | AA42: 研发"中心" | AB42: FALSE | AD42: 0.125 | AE42: 45912.5 | AF42: 正常
A43: ORD-202610-100040 | B43: 45911.5 | C43: C001 | D43: ='客户档案'!B3 -> 张三 | E43: 杭州 | F43: P004 | G43: ='商品目录'!B6 -> 多功能"支架" | H43: 配件 | I43: 10 | J43: 8 | K43: =I43*J43 -> 80 | L43: 0.5 | M43: =K43*L43 -> 40 | N43: 0 | O43: =K43-M43+N43 -> 40 | P43: CNY | Q43: TRUE | R43: 已完成 | S43: 李四 | T43: 网页 | U43: 浙江 | V43: 张三 | W43: 0138000100040 | X43: 第一行 第二行 | Y43: 9.0071993e+15 | Z43: 0 | AA43: 张三 | AB43: TRUE | AD43: 0.125 | AE43: 45913.5 | AF43: 正常
A44: ORD-202610-100041 | B44: 45912.5 | C44: C002 | D44: ='客户档案'!B4 -> Acme, Inc. | E44: 上海 | F44: P001 | G44: ='商品目录'!B3 -> 机械键盘 | H44: 外设 | I44: 2 | J44: 99 | K44: =I44*J44 -> 198 | L44: 0 | M44: =K44*L44 -> 0 | N44: 10 | O44: =K44-M44+N44 -> 208 | P44: CNY | Q44: FALSE | R44: 待付款 | S44: 王五 | T44: 门店 | U44: 上海 | V44: Acme, Inc. | W44: 0138000100041 | Y44: 9.0071993e+15 | Z44: 0 | AA44: Acme, Inc. | AB44: FALSE | AD44: 0.125 | AE44: 45914.5 | AF44: 正常
A45: ORD-202610-100042 | B45: 45913.5 | C45: C003 | D45: ='客户档案'!B5 -> 研发"中心" | E45: 北京 | F45: P002 | G45: ='商品目录'!B4 -> 显示器 | H45: 显示设备 | I45: 4 | J45: 129 | K45: =I45*J45 -> 516 | L45: 0.5 | M45: =K45*L45 -> 258 | N45: 20 | O45: =K45-M45+N45 -> 278 | P45: CNY | Q45: TRUE | R45: 已完成 | S45: 赵六 | T45: API | U45: 北京 | V45: 研发"中心" | W45: 0138000100042 | X45: 加急,周五前送达 | Y45: 9.0071993e+15 | Z45: 0 | AA45: 研发"中心" | AB45: TRUE | AD45: 0.125 | AE45: 45915.5 | AF45: 正常
A46: ORD-202610-100043 | B46: 45914.5 | C46: C001 | D46: ='客户档案'!B3 -> 张三 | E46: 深圳 | F46: P003 | G46: ='商品目录'!B5 -> 办公椅 | H46: 家具 | I46: 6 | J46: 45 | K46: =I46*J46 -> 270 | L46: 0 | M46: =K46*L46 -> 0 | N46: 0 | O46: =K46-M46+N46 -> 270 | P46: CNY | Q46: TRUE | R46: 已完成 | S46: 李四 | T46: 网页 | U46: 广东 | V46: 张三 | W46: 0138000100043 | X46: 收货前联系"前台" | Y46: 9.0071993e+15 | Z46: 0 | AA46: 张三 | AB46: FALSE | AD46: 0.125 | AE46: 45916.5 | AF46: 正常
A47: ORD-202610-100044 | B47: 45915.5 | C47: C002 | D47: ='客户档案'!B4 -> Acme, Inc. | E47: 杭州 | F47: P004 | G47: ='商品目录'!B6 -> 多功能"支架" | H47: 配件 | I47: 8 | J47: 8 | K47: =I47*J47 -> 64 | L47: 0.5 | M47: =K47*L47 -> 32 | N47: 10 | O47: =K47-M47+N47 -> 42 | P47: CNY | Q47: TRUE | R47: 已完成 | S47: 王五 | T47: 门店 | U47: 浙江 | V47: Acme, Inc. | W47: 0138000100044 | X47: 第一行 第二行 | Y47: 9.0071993e+15 | Z47: 0 | AA47: Acme, Inc. | AB47: TRUE | AD47: 0.125 | AE47: 45917.5 | AF47: 正常
A48: ORD-202610-100045 | B48: 45916.5 | C48: C003 | D48: ='客户档案'!B5 -> 研发"中心" | E48: 上海 | F48: P001 | G48: ='商品目录'!B3 -> 机械键盘 | H48: 外设 | I48: 10 | J48: 99 | K48: =I48*J48 -> 990 | L48: 0 | M48: =K48*L48 -> 0 | N48: 20 | O48: =K48-M48+N48 -> 1010 | P48: CNY | Q48: FALSE | R48: 待付款 | S48: 赵六 | T48: API | U48: 上海 | V48: 研发"中心" | W48: 0138000100045 | Y48: 9.0071993e+15 | Z48: 0 | AA48: 研发"中心" | AB48: FALSE | AD48: 0.125 | AE48: 45918.5 | AF48: 正常
A49: ORD-202610-100046 | B49: 45917.5 | C49: C001 | D49: ='客户档案'!B3 -> 张三 | E49: 北京 | F49: P002 | G49: ='商品目录'!B4 -> 显示器 | H49: 显示设备 | I49: 2 | J49: 129 | K49: =I49*J49 -> 258 | L49: 0.5 | M49: =K49*L49 -> 129 | N49: 0 | O49: =K49-M49+N49 -> 129 | P49: CNY | Q49: TRUE | R49: 已完成 | S49: 李四 | T49: 网页 | U49: 北京 | V49: 张三 | W49: 0138000100046 | X49: 加急,周五前送达 | Y49: 9.0071993e+15 | Z49: 0 | AA49: 张三 | AB49: TRUE | AD49: 0.125 | AE49: 45919.5 | AF49: 正常
A50: ORD-202610-100047 | B50: 45918.5 | C50: C002 | D50: ='客户档案'!B4 -> Acme, Inc. | E50: 深圳 | F50: P003 | G50: ='商品目录'!B5 -> 办公椅 | H50: 家具 | I50: 4 | J50: 45 | K50: =I50*J50 -> 180 | L50: 0 | M50: =K50*L50 -> 0 | N50: 10 | O50: =K50-M50+N50 -> 190 | P50: CNY | Q50: TRUE | R50: 已完成 | S50: 王五 | T50: 门店 | U50: 广东 | V50: Acme, Inc. | W50: 0138000100047 | X50: 收货前联系"前台" | Y50: 9.0071993e+15 | Z50: 0 | AA50: Acme, Inc. | AB50: FALSE | AD50: 0.125 | AE50: 45920.5 | AF50: 正常
A51: ORD-202610-100048 | B51: 45919.5 | C51: C003 | D51: ='客户档案'!B5 -> 研发"中心" | E51: 杭州 | F51: P004 | G51: ='商品目录'!B6 -> 多功能"支架" | H51: 配件 | I51: 6 | J51: 8 | K51: =I51*J51 -> 48 | L51: 0.5 | M51: =K51*L51 -> 24 | N51: 20 | O51: =K51-M51+N51 -> 44 | P51: CNY | Q51: TRUE | R51: 已完成 | S51: 赵六 | T51: API | U51: 浙江 | V51: 研发"中心" | W51: 0138000100048 | X51: 第一行 第二行 | Y51: 9.0071993e+15 | Z51: 0 | AA51: 研发"中心" | AB51: TRUE | AD51: 0.125 | AE51: 45921.5 | AF51: 正常
A52: ORD-202610-100049 | B52: 45920.5 | C52: C001 | D52: ='客户档案'!B3 -> 张三 | E52: 上海 | F52: P001 | G52: ='商品目录'!B3 -> 机械键盘 | H52: 外设 | I52: 8 | J52: 99 | K52: =I52*J52 -> 792 | L52: 0 | M52: =K52*L52 -> 0 | N52: 0 | O52: =K52-M52+N52 -> 792 | P52: CNY | Q52: FALSE | R52: 待付款 | S52: 李四 | T52: 网页 | U52: 上海 | V52: 张三 | W52: 0138000100049 | Y52: 9.0071993e+15 | Z52: 0 | AA52: 张三 | AB52: FALSE | AD52: 0.125 | AE52: 45922.5 | AF52: 正常
A53: ORD-202610-100050 | B53: 45921.5 | C53: C002 | D53: ='客户档案'!B4 -> Acme, Inc. | E53: 北京 | F53: P002 | G53: ='商品目录'!B4 -> 显示器 | H53: 显示设备 | I53: 10 | J53: 129 | K53: =I53*J53 -> 1290 | L53: 0.5 | M53: =K53*L53 -> 645 | N53: 10 | O53: =K53-M53+N53 -> 655 | P53: CNY | Q53: TRUE | R53: 已完成 | S53: 王五 | T53: 门店 | U53: 北京 | V53: Acme, Inc. | W53: 0138000100050 | X53: 加急,周五前送达 | Y53: 9.0071993e+15 | Z53: 0 | AA53: Acme, Inc. | AB53: TRUE | AD53: 0.125 | AE53: 45923.5 | AF53: 正常
A54: ORD-202610-100051 | B54: 45922.5 | C54: C003 | D54: ='客户档案'!B5 -> 研发"中心" | E54: 深圳 | F54: P003 | G54: ='商品目录'!B5 -> 办公椅 | H54: 家具 | I54: 2 | J54: 45 | K54: =I54*J54 -> 90 | L54: 0 | M54: =K54*L54 -> 0 | N54: 20 | O54: =K54-M54+N54 -> 110 | P54: CNY | Q54: TRUE | R54: 已完成 | S54: 赵六 | T54: API | U54: 广东 | V54: 研发"中心" | W54: 0138000100051 | X54: 收货前联系"前台" | Y54: 9.0071993e+15 | Z54: 0 | AA54: 研发"中心" | AB54: FALSE | AD54: 0.125 | AE54: 45924.5 | AF54: 正常
A55: ORD-202610-100052 | B55: 45923.5 | C55: C001 | D55: ='客户档案'!B3 -> 张三 | E55: 杭州 | F55: P004 | G55: ='商品目录'!B6 -> 多功能"支架" | H55: 配件 | I55: 4 | J55: 8 | K55: =I55*J55 -> 32 | L55: 0.5 | M55: =K55*L55 -> 16 | N55: 0 | O55: =K55-M55+N55 -> 16 | P55: CNY | Q55: TRUE | R55: 已完成 | S55: 李四 | T55: 网页 | U55: 浙江 | V55: 张三 | W55: 0138000100052 | X55: 第一行 第二行 | Y55: 9.0071993e+15 | Z55: 2 | AA55: 张三 | AB55: TRUE | AD55: 0.125 | AE55: 45925.5 | AF55: 正常
A56: ORD-202610-100053 | B56: 45924.5 | C56: C002 | D56: ='客户档案'!B4 -> Acme, Inc. | E56: 上海 | F56: P001 | G56: ='商品目录'!B3 -> 机械键盘 | H56: 外设 | I56: 6 | J56: 99 | K56: =I56*J56 -> 594 | L56: 0 | M56: =K56*L56 -> 0 | N56: 10 | O56: =K56-M56+N56 -> 604 | P56: CNY | Q56: FALSE | R56: 待付款 | S56: 王五 | T56: 门店 | U56: 上海 | V56: Acme, Inc. | W56: 0138000100053 | Y56: 9.0071993e+15 | Z56: 0 | AA56: Acme, Inc. | AB56: FALSE | AD56: 0.125 | AE56: 45926.5 | AF56: 正常
A57: ORD-202610-100054 | B57: 45925.5 | C57: C003 | D57: ='客户档案'!B5 -> 研发"中心" | E57: 北京 | F57: P002 | G57: ='商品目录'!B4 -> 显示器 | H57: 显示设备 | I57: 8 | J57: 129 | K57: =I57*J57 -> 1032 | L57: 0.5 | M57: =K57*L57 -> 516 | N57: 20 | O57: =K57-M57+N57 -> 536 | P57: CNY | Q57: TRUE | R57: 已完成 | S57: 赵六 | T57: API | U57: 北京 | V57: 研发"中心" | W57: 0138000100054 | X57: 加急,周五前送达 | Y57: 9.0071993e+15 | Z57: 0 | AA57: 研发"中心" | AB57: TRUE | AD57: 0.125 | AE57: 45927.5 | AF57: 正常
A58: ORD-202610-100055 | B58: 45926.5 | C58: C001 | D58: ='客户档案'!B3 -> 张三 | E58: 深圳 | F58: P003 | G58: ='商品目录'!B5 -> 办公椅 | H58: 家具 | I58: 10 | J58: 45 | K58: =I58*J58 -> 450 | L58: 0 | M58: =K58*L58 -> 0 | N58: 0 | O58: =K58-M58+N58 -> 450 | P58: CNY | Q58: TRUE | R58: 已完成 | S58: 李四 | T58: 网页 | U58: 广东 | V58: 张三 | W58: 0138000100055 | X58: 收货前联系"前台" | Y58: 9.0071993e+15 | Z58: 0 | AA58: 张三 | AB58: FALSE | AD58: 0.125 | AE58: 45928.5 | AF58: 正常
A59: ORD-202610-100056 | B59: 45927.5 | C59: C002 | D59: ='客户档案'!B4 -> Acme, Inc. | E59: 杭州 | F59: P004 | G59: ='商品目录'!B6 -> 多功能"支架" | H59: 配件 | I59: 2 | J59: 8 | K59: =I59*J59 -> 16 | L59: 0.5 | M59: =K59*L59 -> 8 | N59: 10 | O59: =K59-M59+N59 -> 18 | P59: CNY | Q59: TRUE | R59: 已完成 | S59: 王五 | T59: 门店 | U59: 浙江 | V59: Acme, Inc. | W59: 0138000100056 | X59: 第一行 第二行 | Y59: 9.0071993e+15 | Z59: 0 | AA59: Acme, Inc. | AB59: TRUE | AD59: 0.125 | AE59: 45929.5 | AF59: 正常
A60: ORD-202610-100057 | B60: 45900.5 | C60: C003 | D60: ='客户档案'!B5 -> 研发"中心" | E60: 上海 | F60: P001 | G60: ='商品目录'!B3 -> 机械键盘 | H60: 外设 | I60: 4 | J60: 99 | K60: =I60*J60 -> 396 | L60: 0 | M60: =K60*L60 -> 0 | N60: 20 | O60: =K60-M60+N60 -> 416 | P60: CNY | Q60: FALSE | R60: 待付款 | S60: 赵六 | T60: API | U60: 上海 | V60: 研发"中心" | W60: 0138000100057 | Y60: 9.0071993e+15 | Z60: 0 | AA60: 研发"中心" | AB60: FALSE | AD60: 0.125 | AE60: 45902.5 | AF60: 正常
A61: ORD-202610-100058 | B61: 45901.5 | C61: C001 | D61: ='客户档案'!B3 -> 张三 | E61: 北京 | F61: P002 | G61: ='商品目录'!B4 -> 显示器 | H61: 显示设备 | I61: 6 | J61: 129 | K61: =I61*J61 -> 774 | L61: 0.5 | M61: =K61*L61 -> 387 | N61: 0 | O61: =K61-M61+N61 -> 387 | P61: CNY | Q61: TRUE | R61: 已完成 | S61: 李四 | T61: 网页 | U61: 北京 | V61: 张三 | W61: 0138000100058 | X61: 加急,周五前送达 | Y61: 9.0071993e+15 | Z61: 0 | AA61: 张三 | AB61: TRUE | AD61: 0.125 | AE61: 45903.5 | AF61: 正常
A62: ORD-202610-100059 | B62: 45902.5 | C62: C002 | D62: ='客户档案'!B4 -> Acme, Inc. | E62: 深圳 | F62: P003 | G62: ='商品目录'!B5 -> 办公椅 | H62: 家具 | I62: 8 | J62: 45 | K62: =I62*J62 -> 360 | L62: 0 | M62: =K62*L62 -> 0 | N62: 10 | O62: =K62-M62+N62 -> 370 | P62: CNY | Q62: TRUE | R62: 已完成 | S62: 王五 | T62: 门店 | U62: 广东 | V62: Acme, Inc. | W62: 0138000100059 | X62: 收货前联系"前台" | Y62: 9.0071993e+15 | Z62: 0 | AA62: Acme, Inc. | AB62: FALSE | AD62: 0.125 | AE62: 45904.5 | AF62: 正常
A63: ORD-202610-100060 | B63: 45903.5 | C63: C003 | D63: ='客户档案'!B5 -> 研发"中心" | E63: 杭州 | F63: P004 | G63: ='商品目录'!B6 -> 多功能"支架" | H63: 配件 | I63: 10 | J63: 8 | K63: =I63*J63 -> 80 | L63: 0.5 | M63: =K63*L63 -> 40 | N63: 20 | O63: =K63-M63+N63 -> 60 | P63: CNY | Q63: TRUE | R63: 已完成 | S63: 赵六 | T63: API | U63: 浙江 | V63: 研发"中心" | W63: 0138000100060 | X63: 第一行 第二行 | Y63: 9.0071993e+15 | Z63: 0 | AA63: 研发"中心" | AB63: TRUE | AD63: 0.125 | AE63: 45905.5 | AF63: 正常
A64: ORD-202610-100061 | B64: 45904.5 | C64: C001 | D64: ='客户档案'!B3 -> 张三 | E64: 上海 | F64: P001 | G64: ='商品目录'!B3 -> 机械键盘 | H64: 外设 | I64: 2 | J64: 99 | K64: =I64*J64 -> 198 | L64: 0 | M64: =K64*L64 -> 0 | N64: 0 | O64: =K64-M64+N64 -> 198 | P64: CNY | Q64: FALSE | R64: 待付款 | S64: 李四 | T64: 网页 | U64: 上海 | V64: 张三 | W64: 0138000100061 | Y64: 9.0071993e+15 | Z64: 0 | AA64: 张三 | AB64: FALSE | AD64: 0.125 | AE64: 45906.5 | AF64: 正常
A65: ORD-202610-100062 | B65: 45905.5 | C65: C002 | D65: ='客户档案'!B4 -> Acme, Inc. | E65: 北京 | F65: P002 | G65: ='商品目录'!B4 -> 显示器 | H65: 显示设备 | I65: 4 | J65: 129 | K65: =I65*J65 -> 516 | L65: 0.5 | M65: =K65*L65 -> 258 | N65: 10 | O65: =K65-M65+N65 -> 268 | P65: CNY | Q65: TRUE | R65: 已完成 | S65: 王五 | T65: 门店 | U65: 北京 | V65: Acme, Inc. | W65: 0138000100062 | X65: 加急,周五前送达 | Y65: 9.0071993e+15 | Z65: 0 | AA65: Acme, Inc. | AB65: TRUE | AD65: 0.125 | AE65: 45907.5 | AF65: 正常
A66: ORD-202610-100063 | B66: 45906.5 | C66: C003 | D66: ='客户档案'!B5 -> 研发"中心" | E66: 深圳 | F66: P003 | G66: ='商品目录'!B5 -> 办公椅 | H66: 家具 | I66: 6 | J66: 45 | K66: =I66*J66 -> 270 | L66: 0 | M66: =K66*L66 -> 0 | N66: 20 | O66: =K66-M66+N66 -> 290 | P66: CNY | Q66: TRUE | R66: 已完成 | S66: 赵六 | T66: API | U66: 广东 | V66: 研发"中心" | W66: 0138000100063 | X66: 收货前联系"前台" | Y66: 9.0071993e+15 | Z66: 0 | AA66: 研发"中心" | AB66: FALSE | AD66: 0.125 | AE66: 45908.5 | AF66: 正常
A67: ORD-202610-100064 | B67: 45907.5 | C67: C001 | D67: ='客户档案'!B3 -> 张三 | E67: 杭州 | F67: P004 | G67: ='商品目录'!B6 -> 多功能"支架" | H67: 配件 | I67: 8 | J67: 8 | K67: =I67*J67 -> 64 | L67: 0.5 | M67: =K67*L67 -> 32 | N67: 0 | O67: =K67-M67+N67 -> 32 | P67: CNY | Q67: TRUE | R67: 已完成 | S67: 李四 | T67: 网页 | U67: 浙江 | V67: 张三 | W67: 0138000100064 | X67: 第一行 第二行 | Y67: 9.0071993e+15 | Z67: 0 | AA67: 张三 | AB67: TRUE | AD67: 0.125 | AE67: 45909.5 | AF67: 正常
A68: ORD-202610-100065 | B68: 45908.5 | C68: C002 | D68: ='客户档案'!B4 -> Acme, Inc. | E68: 上海 | F68: P001 | G68: ='商品目录'!B3 -> 机械键盘 | H68: 外设 | I68: 10 | J68: 99 | K68: =I68*J68 -> 990 | L68: 0 | M68: =K68*L68 -> 0 | N68: 10 | O68: =K68-M68+N68 -> 1000 | P68: CNY | Q68: FALSE | R68: 待付款 | S68: 王五 | T68: 门店 | U68: 上海 | V68: Acme, Inc. | W68: 0138000100065 | Y68: 9.0071993e+15 | Z68: 0 | AA68: Acme, Inc. | AB68: FALSE | AD68: 0.125 | AE68: 45910.5 | AF68: 正常
A69: ORD-202610-100066 | B69: 45909.5 | C69: C003 | D69: ='客户档案'!B5 -> 研发"中心" | E69: 北京 | F69: P002 | G69: ='商品目录'!B4 -> 显示器 | H69: 显示设备 | I69: 2 | J69: 129 | K69: =I69*J69 -> 258 | L69: 0.5 | M69: =K69*L69 -> 129 | N69: 20 | O69: =K69-M69+N69 -> 149 | P69: CNY | Q69: TRUE | R69: 已完成 | S69: 赵六 | T69: API | U69: 北京 | V69: 研发"中心" | W69: 0138000100066 | X69: 加急,周五前送达 | Y69: 9.0071993e+15 | Z69: 0 | AA69: 研发"中心" | AB69: TRUE | AD69: 0.125 | AE69: 45911.5 | AF69: 正常
A70: ORD-202610-100067 | B70: 45910.5 | C70: C001 | D70: ='客户档案'!B3 -> 张三 | E70: 深圳 | F70: P003 | G70: ='商品目录'!B5 -> 办公椅 | H70: 家具 | I70: 4 | J70: 45 | K70: =I70*J70 -> 180 | L70: 0 | M70: =K70*L70 -> 0 | N70: 0 | O70: =K70-M70+N70 -> 180 | P70: CNY | Q70: TRUE | R70: 已完成 | S70: 李四 | T70: 网页 | U70: 广东 | V70: 张三 | W70: 0138000100067 | X70: 收货前联系"前台" | Y70: 9.0071993e+15 | Z70: 0 | AA70: 张三 | AB70: FALSE | AD70: 0.125 | AE70: 45912.5 | AF70: 正常
A71: ORD-202610-100068 | B71: 45911.5 | C71: C002 | D71: ='客户档案'!B4 -> Acme, Inc. | E71: 杭州 | F71: P004 | G71: ='商品目录'!B6 -> 多功能"支架" | H71: 配件 | I71: 6 | J71: 8 | K71: =I71*J71 -> 48 | L71: 0.5 | M71: =K71*L71 -> 24 | N71: 10 | O71: =K71-M71+N71 -> 34 | P71: CNY | Q71: TRUE | R71: 已完成 | S71: 王五 | T71: 门店 | U71: 浙江 | V71: Acme, Inc. | W71: 0138000100068 | X71: 第一行 第二行 | Y71: 9.0071993e+15 | Z71: 0 | AA71: Acme, Inc. | AB71: TRUE | AD71: 0.125 | AE71: 45913.5 | AF71: 正常
A72: ORD-202610-100069 | B72: 45912.5 | C72: C003 | D72: ='客户档案'!B5 -> 研发"中心" | E72: 上海 | F72: P001 | G72: ='商品目录'!B3 -> 机械键盘 | H72: 外设 | I72: 8 | J72: 99 | K72: =I72*J72 -> 792 | L72: 0 | M72: =K72*L72 -> 0 | N72: 20 | O72: =K72-M72+N72 -> 812 | P72: CNY | Q72: FALSE | R72: 待付款 | S72: 赵六 | T72: API | U72: 上海 | V72: 研发"中心" | W72: 0138000100069 | Y72: 9.0071993e+15 | Z72: 2 | AA72: 研发"中心" | AB72: FALSE | AD72: 0.125 | AE72: 45914.5 | AF72: 正常
A73: ORD-202610-100070 | B73: 45913.5 | C73: C001 | D73: ='客户档案'!B3 -> 张三 | E73: 北京 | F73: P002 | G73: ='商品目录'!B4 -> 显示器 | H73: 显示设备 | I73: 10 | J73: 129 | K73: =I73*J73 -> 1290 | L73: 0.5 | M73: =K73*L73 -> 645 | N73: 0 | O73: =K73-M73+N73 -> 645 | P73: CNY | Q73: TRUE | R73: 已完成 | S73: 李四 | T73: 网页 | U73: 北京 | V73: 张三 | W73: 0138000100070 | X73: 加急,周五前送达 | Y73: 9.0071993e+15 | Z73: 0 | AA73: 张三 | AB73: TRUE | AD73: 0.125 | AE73: 45915.5 | AF73: 正常
A74: ORD-202610-100071 | B74: 45914.5 | C74: C002 | D74: ='客户档案'!B4 -> Acme, Inc. | E74: 深圳 | F74: P003 | G74: ='商品目录'!B5 -> 办公椅 | H74: 家具 | I74: 2 | J74: 45 | K74: =I74*J74 -> 90 | L74: 0 | M74: =K74*L74 -> 0 | N74: 10 | O74: =K74-M74+N74 -> 100 | P74: CNY | Q74: TRUE | R74: 已完成 | S74: 王五 | T74: 门店 | U74: 广东 | V74: Acme, Inc. | W74: 0138000100071 | X74: 收货前联系"前台" | Y74: 9.0071993e+15 | Z74: 0 | AA74: Acme, Inc. | AB74: FALSE | AD74: 0.125 | AE74: 45916.5 | AF74: 正常
A75: ORD-202610-100072 | B75: 45915.5 | C75: C003 | D75: ='客户档案'!B5 -> 研发"中心" | E75: 杭州 | F75: P004 | G75: ='商品目录'!B6 -> 多功能"支架" | H75: 配件 | I75: 4 | J75: 8 | K75: =I75*J75 -> 32 | L75: 0.5 | M75: =K75*L75 -> 16 | N75: 20 | O75: =K75-M75+N75 -> 36 | P75: CNY | Q75: TRUE | R75: 已完成 | S75: 赵六 | T75: API | U75: 浙江 | V75: 研发"中心" | W75: 0138000100072 | X75: 第一行 第二行 | Y75: 9.0071993e+15 | Z75: 0 | AA75: 研发"中心" | AB75: TRUE | AD75: 0.125 | AE75: 45917.5 | AF75: 正常
A76: ORD-202610-100073 | B76: 45916.5 | C76: C001 | D76: ='客户档案'!B3 -> 张三 | E76: 上海 | F76: P001 | G76: ='商品目录'!B3 -> 机械键盘 | H76: 外设 | I76: 6 | J76: 99 | K76: =I76*J76 -> 594 | L76: 0 | M76: =K76*L76 -> 0 | N76: 0 | O76: =K76-M76+N76 -> 594 | P76: CNY | Q76: FALSE | R76: 待付款 | S76: 李四 | T76: 网页 | U76: 上海 | V76: 张三 | W76: 0138000100073 | Y76: 9.0071993e+15 | Z76: 0 | AA76: 张三 | AB76: FALSE | AD76: 0.125 | AE76: 45918.5 | AF76: 正常
A77: ORD-202610-100074 | B77: 45917.5 | C77: C002 | D77: ='客户档案'!B4 -> Acme, Inc. | E77: 北京 | F77: P002 | G77: ='商品目录'!B4 -> 显示器 | H77: 显示设备 | I77: 8 | J77: 129 | K77: =I77*J77 -> 1032 | L77: 0.5 | M77: =K77*L77 -> 516 | N77: 10 | O77: =K77-M77+N77 -> 526 | P77: CNY | Q77: TRUE | R77: 已完成 | S77: 王五 | T77: 门店 | U77: 北京 | V77: Acme, Inc. | W77: 0138000100074 | X77: 加急,周五前送达 | Y77: 9.0071993e+15 | Z77: 0 | AA77: Acme, Inc. | AB77: TRUE | AD77: 0.125 | AE77: 45919.5 | AF77: 正常
A78: ORD-202610-100075 | B78: 45918.5 | C78: C003 | D78: ='客户档案'!B5 -> 研发"中心" | E78: 深圳 | F78: P003 | G78: ='商品目录'!B5 -> 办公椅 | H78: 家具 | I78: 10 | J78: 45 | K78: =I78*J78 -> 450 | L78: 0 | M78: =K78*L78 -> 0 | N78: 20 | O78: =K78-M78+N78 -> 470 | P78: CNY | Q78: TRUE | R78: 已完成 | S78: 赵六 | T78: API | U78: 广东 | V78: 研发"中心" | W78: 0138000100075 | X78: 收货前联系"前台" | Y78: 9.0071993e+15 | Z78: 0 | AA78: 研发"中心" | AB78: FALSE | AD78: 0.125 | AE78: 45920.5 | AF78: 正常
A79: ORD-202610-100076 | B79: 45919.5 | C79: C001 | D79: ='客户档案'!B3 -> 张三 | E79: 杭州 | F79: P004 | G79: ='商品目录'!B6 -> 多功能"支架" | H79: 配件 | I79: 2 | J79: 8 | K79: =I79*J79 -> 16 | L79: 0.5 | M79: =K79*L79 -> 8 | N79: 0 | O79: =K79-M79+N79 -> 8 | P79: CNY | Q79: TRUE | R79: 已完成 | S79: 李四 | T79: 网页 | U79: 浙江 | V79: 张三 | W79: 0138000100076 | X79: 第一行 第二行 | Y79: 9.0071993e+15 | Z79: 0 | AA79: 张三 | AB79: TRUE | AD79: 0.125 | AE79: 45921.5 | AF79: 正常
A80: ORD-202610-100077 | B80: 45920.5 | C80: C002 | D80: ='客户档案'!B4 -> Acme, Inc. | E80: 上海 | F80: P001 | G80: ='商品目录'!B3 -> 机械键盘 | H80: 外设 | I80: 4 | J80: 99 | K80: =I80*J80 -> 396 | L80: 0 | M80: =K80*L80 -> 0 | N80: 10 | O80: =K80-M80+N80 -> 406 | P80: CNY | Q80: FALSE | R80: 待付款 | S80: 王五 | T80: 门店 | U80: 上海 | V80: Acme, Inc. | W80: 0138000100077 | Y80: 9.0071993e+15 | Z80: 0 | AA80: Acme, Inc. | AB80: FALSE | AD80: 0.125 | AE80: 45922.5 | AF80: 正常
A81: ORD-202610-100078 | B81: 45921.5 | C81: C003 | D81: ='客户档案'!B5 -> 研发"中心" | E81: 北京 | F81: P002 | G81: ='商品目录'!B4 -> 显示器 | H81: 显示设备 | I81: 6 | J81: 129 | K81: =I81*J81 -> 774 | L81: 0.5 | M81: =K81*L81 -> 387 | N81: 20 | O81: =K81-M81+N81 -> 407 | P81: CNY | Q81: TRUE | R81: 已完成 | S81: 赵六 | T81: API | U81: 北京 | V81: 研发"中心" | W81: 0138000100078 | X81: 加急,周五前送达 | Y81: 9.0071993e+15 | Z81: 0 | AA81: 研发"中心" | AB81: TRUE | AD81: 0.125 | AE81: 45923.5 | AF81: 正常
A82: ORD-202610-100079 | B82: 45922.5 | C82: C001 | D82: ='客户档案'!B3 -> 张三 | E82: 深圳 | F82: P003 | G82: ='商品目录'!B5 -> 办公椅 | H82: 家具 | I82: 8 | J82: 45 | K82: =I82*J82 -> 360 | L82: 0 | M82: =K82*L82 -> 0 | N82: 0 | O82: =K82-M82+N82 -> 360 | P82: CNY | Q82: TRUE | R82: 已完成 | S82: 李四 | T82: 网页 | U82: 广东 | V82: 张三 | W82: 0138000100079 | X82: 收货前联系"前台" | Y82: 9.0071993e+15 | Z82: 0 | AA82: 张三 | AB82: FALSE | AD82: 0.125 | AE82: 45924.5 | AF82: 正常
A83: ORD-202610-100080 | B83: 45923.5 | C83: C002 | D83: ='客户档案'!B4 -> Acme, Inc. | E83: 杭州 | F83: P004 | G83: ='商品目录'!B6 -> 多功能"支架" | H83: 配件 | I83: 10 | J83: 8 | K83: =I83*J83 -> 80 | L83: 0.5 | M83: =K83*L83 -> 40 | N83: 10 | O83: =K83-M83+N83 -> 50 | P83: CNY | Q83: TRUE | R83: 已完成 | S83: 王五 | T83: 门店 | U83: 浙江 | V83: Acme, Inc. | W83: 0138000100080 | X83: 第一行 第二行 | Y83: 9.0071993e+15 | Z83: 0 | AA83: Acme, Inc. | AB83: TRUE | AD83: 0.125 | AE83: 45925.5 | AF83: 正常
A84: ORD-202610-100081 | B84: 45924.5 | C84: C003 | D84: ='客户档案'!B5 -> 研发"中心" | E84: 上海 | F84: P001 | G84: ='商品目录'!B3 -> 机械键盘 | H84: 外设 | I84: 2 | J84: 99 | K84: =I84*J84 -> 198 | L84: 0 | M84: =K84*L84 -> 0 | N84: 20 | O84: =K84-M84+N84 -> 218 | P84: CNY | Q84: FALSE | R84: 待付款 | S84: 赵六 | T84: API | U84: 上海 | V84: 研发"中心" | W84: 0138000100081 | Y84: 9.0071993e+15 | Z84: 0 | AA84: 研发"中心" | AB84: FALSE | AD84: 0.125 | AE84: 45926.5 | AF84: 正常
A85: ORD-202610-100082 | B85: 45925.5 | C85: C001 | D85: ='客户档案'!B3 -> 张三 | E85: 北京 | F85: P002 | G85: ='商品目录'!B4 -> 显示器 | H85: 显示设备 | I85: 4 | J85: 129 | K85: =I85*J85 -> 516 | L85: 0.5 | M85: =K85*L85 -> 258 | N85: 0 | O85: =K85-M85+N85 -> 258 | P85: CNY | Q85: TRUE | R85: 已完成 | S85: 李四 | T85: 网页 | U85: 北京 | V85: 张三 | W85: 0138000100082 | X85: 加急,周五前送达 | Y85: 9.0071993e+15 | Z85: 0 | AA85: 张三 | AB85: TRUE | AD85: 0.125 | AE85: 45927.5 | AF85: 正常
A86: ORD-202610-100083 | B86: 45926.5 | C86: C002 | D86: ='客户档案'!B4 -> Acme, Inc. | E86: 深圳 | F86: P003 | G86: ='商品目录'!B5 -> 办公椅 | H86: 家具 | I86: 6 | J86: 45 | K86: =I86*J86 -> 270 | L86: 0 | M86: =K86*L86 -> 0 | N86: 10 | O86: =K86-M86+N86 -> 280 | P86: CNY | Q86: TRUE | R86: 已完成 | S86: 王五 | T86: 门店 | U86: 广东 | V86: Acme, Inc. | W86: 0138000100083 | X86: 收货前联系"前台" | Y86: 9.0071993e+15 | Z86: 0 | AA86: Acme, Inc. | AB86: FALSE | AD86: 0.125 | AE86: 45928.5 | AF86: 正常
A87: ORD-202610-100084 | B87: 45927.5 | C87: C003 | D87: ='客户档案'!B5 -> 研发"中心" | E87: 杭州 | F87: P004 | G87: ='商品目录'!B6 -> 多功能"支架" | H87: 配件 | I87: 8 | J87: 8 | K87: =I87*J87 -> 64 | L87: 0.5 | M87: =K87*L87 -> 32 | N87: 20 | O87: =K87-M87+N87 -> 52 | P87: CNY | Q87: TRUE | R87: 已完成 | S87: 赵六 | T87: API | U87: 浙江 | V87: 研发"中心" | W87: 0138000100084 | X87: 第一行 第二行 | Y87: 9.0071993e+15 | Z87: 0 | AA87: 研发"中心" | AB87: TRUE | AD87: 0.125 | AE87: 45929.5 | AF87: 正常
A88: ORD-202610-100085 | B88: 45900.5 | C88: C001 | D88: ='客户档案'!B3 -> 张三 | E88: 上海 | F88: P001 | G88: ='商品目录'!B3 -> 机械键盘 | H88: 外设 | I88: 10 | J88: 99 | K88: =I88*J88 -> 990 | L88: 0 | M88: =K88*L88 -> 0 | N88: 0 | O88: =K88-M88+N88 -> 990 | P88: CNY | Q88: FALSE | R88: 待付款 | S88: 李四 | T88: 网页 | U88: 上海 | V88: 张三 | W88: 0138000100085 | Y88: 9.0071993e+15 | Z88: 0 | AA88: 张三 | AB88: FALSE | AD88: 0.125 | AE88: 45902.5 | AF88: 正常
A89: ORD-202610-100086 | B89: 45901.5 | C89: C002 | D89: ='客户档案'!B4 -> Acme, Inc. | E89: 北京 | F89: P002 | G89: ='商品目录'!B4 -> 显示器 | H89: 显示设备 | I89: 2 | J89: 129 | K89: =I89*J89 -> 258 | L89: 0.5 | M89: =K89*L89 -> 129 | N89: 10 | O89: =K89-M89+N89 -> 139 | P89: CNY | Q89: TRUE | R89: 已完成 | S89: 王五 | T89: 门店 | U89: 北京 | V89: Acme, Inc. | W89: 0138000100086 | X89: 加急,周五前送达 | Y89: 9.0071993e+15 | Z89: 2 | AA89: Acme, Inc. | AB89: TRUE | AD89: 0.125 | AE89: 45903.5 | AF89: 正常
A90: ORD-202610-100087 | B90: 45902.5 | C90: C003 | D90: ='客户档案'!B5 -> 研发"中心" | E90: 深圳 | F90: P003 | G90: ='商品目录'!B5 -> 办公椅 | H90: 家具 | I90: 4 | J90: 45 | K90: =I90*J90 -> 180 | L90: 0 | M90: =K90*L90 -> 0 | N90: 20 | O90: =K90-M90+N90 -> 200 | P90: CNY | Q90: TRUE | R90: 已完成 | S90: 赵六 | T90: API | U90: 广东 | V90: 研发"中心" | W90: 0138000100087 | X90: 收货前联系"前台" | Y90: 9.0071993e+15 | Z90: 0 | AA90: 研发"中心" | AB90: FALSE | AD90: 0.125 | AE90: 45904.5 | AF90: 正常
A91: ORD-202610-100088 | B91: 45903.5 | C91: C001 | D91: ='客户档案'!B3 -> 张三 | E91: 杭州 | F91: P004 | G91: ='商品目录'!B6 -> 多功能"支架" | H91: 配件 | I91: 6 | J91: 8 | K91: =I91*J91 -> 48 | L91: 0.5 | M91: =K91*L91 -> 24 | N91: 0 | O91: =K91-M91+N91 -> 24 | P91: CNY | Q91: TRUE | R91: 已完成 | S91: 李四 | T91: 网页 | U91: 浙江 | V91: 张三 | W91: 0138000100088 | X91: 第一行 第二行 | Y91: 9.0071993e+15 | Z91: 0 | AA91: 张三 | AB91: TRUE | AD91: 0.125 | AE91: 45905.5 | AF91: 正常
A92: ORD-202610-100089 | B92: 45904.5 | C92: C002 | D92: ='客户档案'!B4 -> Acme, Inc. | E92: 上海 | F92: P001 | G92: ='商品目录'!B3 -> 机械键盘 | H92: 外设 | I92: 8 | J92: 99 | K92: =I92*J92 -> 792 | L92: 0 | M92: =K92*L92 -> 0 | N92: 10 | O92: =K92-M92+N92 -> 802 | P92: CNY | Q92: FALSE | R92: 待付款 | S92: 王五 | T92: 门店 | U92: 上海 | V92: Acme, Inc. | W92: 0138000100089 | Y92: 9.0071993e+15 | Z92: 0 | AA92: Acme, Inc. | AB92: FALSE | AD92: 0.125 | AE92: 45906.5 | AF92: 正常
A93: ORD-202610-100090 | B93: 45905.5 | C93: C003 | D93: ='客户档案'!B5 -> 研发"中心" | E93: 北京 | F93: P002 | G93: ='商品目录'!B4 -> 显示器 | H93: 显示设备 | I93: 10 | J93: 129 | K93: =I93*J93 -> 1290 | L93: 0.5 | M93: =K93*L93 -> 645 | N93: 20 | O93: =K93-M93+N93 -> 665 | P93: CNY | Q93: TRUE | R93: 已完成 | S93: 赵六 | T93: API | U93: 北京 | V93: 研发"中心" | W93: 0138000100090 | X93: 加急,周五前送达 | Y93: 9.0071993e+15 | Z93: 0 | AA93: 研发"中心" | AB93: TRUE | AD93: 0.125 | AE93: 45907.5 | AF93: 正常
A94: ORD-202610-100091 | B94: 45906.5 | C94: C001 | D94: ='客户档案'!B3 -> 张三 | E94: 深圳 | F94: P003 | G94: ='商品目录'!B5 -> 办公椅 | H94: 家具 | I94: 2 | J94: 45 | K94: =I94*J94 -> 90 | L94: 0 | M94: =K94*L94 -> 0 | N94: 0 | O94: =K94-M94+N94 -> 90 | P94: CNY | Q94: TRUE | R94: 已完成 | S94: 李四 | T94: 网页 | U94: 广东 | V94: 张三 | W94: 0138000100091 | X94: 收货前联系"前台" | Y94: 9.0071993e+15 | Z94: 0 | AA94: 张三 | AB94: FALSE | AD94: 0.125 | AE94: 45908.5 | AF94: 正常
A95: ORD-202610-100092 | B95: 45907.5 | C95: C002 | D95: ='客户档案'!B4 -> Acme, Inc. | E95: 杭州 | F95: P004 | G95: ='商品目录'!B6 -> 多功能"支架" | H95: 配件 | I95: 4 | J95: 8 | K95: =I95*J95 -> 32 | L95: 0.5 | M95: =K95*L95 -> 16 | N95: 10 | O95: =K95-M95+N95 -> 26 | P95: CNY | Q95: TRUE | R95: 已完成 | S95: 王五 | T95: 门店 | U95: 浙江 | V95: Acme, Inc. | W95: 0138000100092 | X95: 第一行 第二行 | Y95: 9.0071993e+15 | Z95: 0 | AA95: Acme, Inc. | AB95: TRUE | AD95: 0.125 | AE95: 45909.5 | AF95: 正常
A96: ORD-202610-100093 | B96: 45908.5 | C96: C003 | D96: ='客户档案'!B5 -> 研发"中心" | E96: 上海 | F96: P001 | G96: ='商品目录'!B3 -> 机械键盘 | H96: 外设 | I96: 6 | J96: 99 | K96: =I96*J96 -> 594 | L96: 0 | M96: =K96*L96 -> 0 | N96: 20 | O96: =K96-M96+N96 -> 614 | P96: CNY | Q96: FALSE | R96: 待付款 | S96: 赵六 | T96: API | U96: 上海 | V96: 研发"中心" | W96: 0138000100093 | Y96: 9.0071993e+15 | Z96: 0 | AA96: 研发"中心" | AB96: FALSE | AD96: 0.125 | AE96: 45910.5 | AF96: 正常
A97: ORD-202610-100094 | B97: 45909.5 | C97: C001 | D97: ='客户档案'!B3 -> 张三 | E97: 北京 | F97: P002 | G97: ='商品目录'!B4 -> 显示器 | H97: 显示设备 | I97: 8 | J97: 129 | K97: =I97*J97 -> 1032 | L97: 0.5 | M97: =K97*L97 -> 516 | N97: 0 | O97: =K97-M97+N97 -> 516 | P97: CNY | Q97: TRUE | R97: 已完成 | S97: 李四 | T97: 网页 | U97: 北京 | V97: 张三 | W97: 0138000100094 | X97: 加急,周五前送达 | Y97: 9.0071993e+15 | Z97: 0 | AA97: 张三 | AB97: TRUE | AD97: 0.125 | AE97: 45911.5 | AF97: 正常
A98: ORD-202610-100095 | B98: 45910.5 | C98: C002 | D98: ='客户档案'!B4 -> Acme, Inc. | E98: 深圳 | F98: P003 | G98: ='商品目录'!B5 -> 办公椅 | H98: 家具 | I98: 10 | J98: 45 | K98: =I98*J98 -> 450 | L98: 0 | M98: =K98*L98 -> 0 | N98: 10 | O98: =K98-M98+N98 -> 460 | P98: CNY | Q98: TRUE | R98: 已完成 | S98: 王五 | T98: 门店 | U98: 广东 | V98: Acme, Inc. | W98: 0138000100095 | X98: 收货前联系"前台" | Y98: 9.0071993e+15 | Z98: 0 | AA98: Acme, Inc. | AB98: FALSE | AD98: 0.125 | AE98: 45912.5 | AF98: 正常
A99: ORD-202610-100096 | B99: 45911.5 | C99: C003 | D99: ='客户档案'!B5 -> 研发"中心" | E99: 杭州 | F99: P004 | G99: ='商品目录'!B6 -> 多功能"支架" | H99: 配件 | I99: 2 | J99: 8 | K99: =I99*J99 -> 16 | L99: 0.5 | M99: =K99*L99 -> 8 | N99: 20 | O99: =K99-M99+N99 -> 28 | P99: CNY | Q99: TRUE | R99: 已完成 | S99: 赵六 | T99: API | U99: 浙江 | V99: 研发"中心" | W99: 0138000100096 | X99: 第一行 第二行 | Y99: 9.0071993e+15 | Z99: 0 | AA99: 研发"中心" | AB99: TRUE | AD99: 0.125 | AE99: 45913.5 | AF99: 正常
A100: ORD-202610-100097 | B100: 45912.5 | C100: C001 | D100: ='客户档案'!B3 -> 张三 | E100: 上海 | F100: P001 | G100: ='商品目录'!B3 -> 机械键盘 | H100: 外设 | I100: 4 | J100: 99 | K100: =I100*J100 -> 396 | L100: 0 | M100: =K100*L100 -> 0 | N100: 0 | O100: =K100-M100+N100 -> 396 | P100: CNY | Q100: FALSE | R100: 待付款 | S100: 李四 | T100: 网页 | U100: 上海 | V100: 张三 | W100: 0138000100097 | Y100: 9.0071993e+15 | Z100: 0 | AA100: 张三 | AB100: FALSE | AD100: 0.125 | AE100: 45914.5 | AF100: 正常
...

Sheet 商品目录
A1: 商品目录与库存
A2: 商品编号 | B2: 名称 | C2: 分类 | D2: 单价 | E2: 库存 | F2: 在售 | G2: 说明
A3: P001 | B3: 机械键盘 | C3: 外设 | D3: 99 | E3: 1000 | F3: TRUE | G3: 仓库,需复核
A4: P002 | B4: 显示器 | C4: 显示设备 | D4: 129 | E4: 800 | F4: TRUE | G4: 仓库,需复核
A5: P003 | B5: 办公椅 | C5: 家具 | D5: 45 | E5: 600 | F5: TRUE | G5: 仓库,需复核
A6: P004 | B6: 多功能"支架" | C6: 配件 | D6: 8 | E6: 400 | F6: FALSE | G6: 仓库,需复核

Sheet 客户档案
A1: 客户主数据
A2: 客户编号 | B2: 名称 | C2: 电话 | D2: 地区 | E2: 等级 | F2: 注册日期 | G2: 启用 | H2: 备注
A3: C001 | B3: 张三 | C3: 0013800012345 | D3: 上海 | E3: 普通 | F3: 45000.5 | G3: TRUE | H3: 首选联系人 备用联系人
A4: C002 | B4: Acme, Inc. | C4: 0013800012345 | D4: 北京 | E4: VIP | F4: 45001.5 | G4: TRUE | H4: 首选联系人 备用联系人
A5: C003 | B5: 研发"中心" | C5: 0013800012345 | D5: 深圳 | E5: VIP | F5: 45002.5 | G5: TRUE | H5: 首选联系人 备用联系人

Sheet 月度汇总
A1: 月度经营汇总
A2: 指标 | B2: 数值 | C2: 口径 | F2: 备注
A3: 订单数 | B3: =COUNTA('订单明细'!A4:A1007) -> 1000 | C3: 不含分隔空行
A4: 原价金额 | B4: =SUM('订单明细'!K4:K1007) -> 421500 | C4: 含隐藏行
A5: 优惠金额 | B5: =SUM('订单明细'!M4:M1007) -> 102750
A6: 运费 | B6: =SUM('订单明细'!N4:N1007) -> 9990
A7: 应付金额 | B7: =SUM('订单明细'!O4:O1007) -> 328740
A8: 已付款订单 | B8: =COUNTIF('订单明细'!Q4:Q1007,TRUE) -> 750
A9: 欠款金额 | B9: =SUMIF('订单明细'!Q4:Q1007,FALSE,'订单明细'!O4:O1007) -> 150990

Sheet 说明与异常
A1: 数据字典与异常样例
A2: 场景 | B2: 整数 | C2: 小数 | D2: 布尔 | E2: 文本 | F2: 错误 | G2: 日期 | H2: 备注
A3: 负数与零 | B3: -100 | C3: -0.125 | D3: FALSE | E3: 00000
A4: 异常计算 | B4: 0 | D4: TRUE | E4: 待修复 | F4: #DIV/0!
A5: 缺失关联 | F5: #N/A | H5: 客户,商品缺失
A6: 非法值 | F6: #VALUE! | H6: 检查"类型"
A7: 时间字段 | G7: 45900.5 | H7: 底层日期序列数
